loginator/__init__.py
loginator/__version__.py
loginator/loginator.py
loginator-0.0.16.dist-info/LICENSE
loginator-0.0.16.dist-info/METADATA
loginator-0.0.16.dist-info/WHEEL
loginator-0.0.16.dist-info/entry_points.txt
loginator-0.0.16.dist-info/top_level.txt
loginator-0.0.16.dist-info/RECORD
